{
    "comments": [
        { "username": "Alice", "content": "This is a great post!", "createdAt": "2023-10-01T12:00:00Z" },
        { "username": "Bob", "content": "Thanks for sharing!", "createdAt": "2023-10-01T12:00:00Z" },
        { "username": "Charlie", "content": "I found this very helpful.", "createdAt": "2023-10-01T12:00:00Z" }
    ],
    "posts": [
        {
            "username": "Alice",
            "type": "Informative",
            "title": "Understanding Mongoose",
            "content": "Mongoose is a powerful tool for MongoDB.",
            "imgURL": "http://example.com/image1.jpg",
            "likes": 10,
            "dislikes": 2,
            "createdAt": "2023-10-01T12:00:00Z"
        },
        {
            "username": "Bob",
            "type": "Opinion",
            "title": "Why I Love MongoDB",
            "content": "MongoDB is great for unstructured data.",
            "imgURL": "http://example.com/image2.jpg",
            "likes": 5,
            "dislikes": 1,
            "createdAt": "2023-10-01T12:00:00Z"
        }
    ],
    "users": [
        {
            "username": "Alice",
            "email": "alice@example.com",
            "password": "password123"
        },
        {
            "username": "Bob",
            "email": "bob@example.com",
            "password": "password456"
        },
        {
            "username": "Charlie",
            "email": "charlie@example.com",
            "password": "password789"
        }
    ]
}
